__init__.py
biometeo_frontend/__init__.py
biometeo_frontend/main.py
biometeo_frontend-0.1.1.dist-info/METADATA
biometeo_frontend-0.1.1.dist-info/WHEEL
biometeo_frontend-0.1.1.dist-info/entry_points.txt
biometeo_frontend-0.1.1.dist-info/top_level.txt
biometeo_frontend-0.1.1.dist-info/RECORD
