Metadata-Version: 2.4
Name: biometeo-frontend
Version: 0.1.1
Summary: A friendly UI app designed for biometeo, shows function documentation, default values
Requires-Python: >=3.10
Requires-Dist: biometeo==0.4.0
Requires-Dist: customtkinter>=5.2.2
Requires-Dist: pandas>=2.3.3
Requires-Dist: tkinterdnd2>=0.4.3
